{"cameraMode":{"drawMode":0,"name":"Shaded","section":"Shading Mode"},"sceneLighting":false,"audioPlay":false,"sceneViewState":{"showFog":true,"showMaterialUpdate":false,"showSkybox":false,"showFlares":true,"showImageEffects":true,"showParticleSystems":true},"in2DMode":false,"pivot":{"x":0.013581648468971253,"y":2.02272367477417,"z":0.9344985485076904},"rotation":{"x":0.019181715324521066,"y":-0.9171270728111267,"z":0.39577606320381167,"w":0.04430657625198364},"size":3.1578853130340578,"orthographic":false}